netband.py
netband-2.1.6.data/data/man/man1/netband.1
netband-2.1.6.dist-info/LICENSE
netband-2.1.6.dist-info/METADATA
netband-2.1.6.dist-info/WHEEL
netband-2.1.6.dist-info/entry_points.txt
netband-2.1.6.dist-info/top_level.txt
netband-2.1.6.dist-info/RECORD
