Metadata-Version: 2.1
Name: netband
Version: 2.1.6
Summary: Command line interface for testing internet bandwidth using speedtest.net
Home-page: https://github.com/xunicatt/netband
Author: Aniket Biswas
Author-email: contact.aniket.biswas@gmail.com
License: Apache License, Version 2.0
Keywords: netband speedtest speedtest.net
Classifier: Development Status :: 5 - Production/Stable
Classifier: Programming Language :: Python
Classifier: Environment :: Console
Classifier: License :: OSI Approved :: Apache Software License
Classifier: Operating System :: OS Independent
Classifier: Programming Language :: Python :: 2
Classifier: Programming Language :: Python :: 2.4
Classifier: Programming Language :: Python :: 2.5
Classifier: Programming Language :: Python :: 2.6
Classifier: Programming Language :: Python :: 2.7
Classifier: Programming Language :: Python :: 3
Classifier: Programming Language :: Python :: 3.1
Classifier: Programming Language :: Python :: 3.2
Classifier: Programming Language :: Python :: 3.3
Classifier: Programming Language :: Python :: 3.4
Classifier: Programming Language :: Python :: 3.5
Classifier: Programming Language :: Python :: 3.6
Classifier: Programming Language :: Python :: 3.7
Classifier: Programming Language :: Python :: 3.8
Classifier: Programming Language :: Python :: 3.9
Classifier: Programming Language :: Python :: 3.10
License-File: LICENSE
